Github_download/Git_down.py
Github_download/__init__.py
Github_download/__main__.py
github_download-0.0.1.dist-info/METADATA
github_download-0.0.1.dist-info/WHEEL
github_download-0.0.1.dist-info/entry_points.txt
github_download-0.0.1.dist-info/top_level.txt
github_download-0.0.1.dist-info/zip-safe
github_download-0.0.1.dist-info/RECORD
