Metadata-Version: 2.1
Name: github-download
Version: 0.0.1
Summary: a command line tool for camel case
Home-page: UNKNOWN
Author: UNKNOWN
Author-email: 1223411083@qq.com
License: MIT
Keywords: Github_Download
Platform: UNKNOWN
Requires-Dist: requests
Requires-Dist: lxml
Requires-Dist: Beautifulsoup4
